{"v":"5.9.6","fr":60,"ip":0,"op":120,"w":750,"h":750,"nm":"Main render","ddd":0,"assets":[],"layers":[{"ddd":0,"ind":1,"ty":4,"nm":"Layer 2","sr":1,"ks":{"o":{"a":0,"k":100,"ix":11},"r":{"a":0,"k":0,"ix":10},"p":{"a":0,"k":[375,375.941,0],"ix":2,"l":2},"a":{"a":0,"k":[375,375.941,0],"ix":1,"l":2},"s":{"a":0,"k":[100,100,100],"ix":6,"l":2}},"ao":0,"shapes":[{"ty":"gr","it":[{"ty":"gr","it":[{"ty":"gr","it":[{"ind":0,"ty":"sh","ix":1,"ks":{"a":1,"k":[{"i":{"x":0.667,"y":1},"o":{"x":0.333,"y":0},"t":3,"s":[{"i":[[0,0],[0,0],[0,0]],"o":[[0,0],[0,0],[0,0]],"v":[[26.835,-12.176],[-7.688,12.176],[-26.835,4.618]],"c":false}]},{"i":{"x":0.667,"y":1},"o":{"x":0.333,"y":0},"t":13,"s":[{"i":[[0,0],[0,0],[0,0]],"o":[[0,0],[0,0],[0,0]],"v":[[19.11,-63.599],[-15.414,-39.246],[-34.561,-46.805]],"c":false}]},{"i":{"x":0.667,"y":1},"o":{"x":0.333,"y":0},"t":23,"s":[{"i":[[0,0],[0,0],[0,0]],"o":[[0,0],[0,0],[0,0]],"v":[[19.11,-63.599],[-15.414,-39.246],[-34.561,-46.805]],"c":false}]},{"i":{"x":0.667,"y":1},"o":{"x":0.333,"y":0},"t":33,"s":[{"i":[[0,0],[0,0],[0,0]],"o":[[0,0],[0,0],[0,0]],"v":[[26.835,-36.176],[-7.688,-11.824],[-26.835,-19.382]],"c":false}]},{"t":43,"s":[{"i":[[0,0],[0,0],[0,0]],"o":[[0,0],[0,0],[0,0]],"v":[[26.835,-12.176],[-7.688,12.176],[-26.835,4.618]],"c":false}]}],"ix":2},"nm":"Path 1","mn":"ADBE Vector Shape - Group","hd":false},{"ty":"st","c":{"a":0,"k":[0,0,0,1],"ix":3},"o":{"a":0,"k":100,"ix":4},"w":{"a":0,"k":18,"ix":5},"lc":2,"lj":2,"bm":0,"nm":"Stroke 1","mn":"ADBE Vector Graphic - Stroke","hd":false},{"ty":"tr","p":{"a":0,"k":[382.688,362.824],"ix":2},"a":{"a":0,"k":[0,0],"ix":1},"s":{"a":0,"k":[100,100],"ix":3},"r":{"a":0,"k":0,"ix":6},"o":{"a":0,"k":100,"ix":7},"sk":{"a":0,"k":0,"ix":4},"sa":{"a":0,"k":0,"ix":5},"nm":"Transform"}],"nm":"Group 1","np":2,"cix":2,"bm":0,"ix":1,"mn":"ADBE Vector Group","hd":false},{"ty":"gr","it":[{"ind":0,"ty":"sh","ix":1,"ks":{"a":1,"k":[{"i":{"x":0.667,"y":1},"o":{"x":0.333,"y":0},"t":3,"s":[{"i":[[-51.655,0],[0,-51.655],[51.655,0],[0,51.655]],"o":[[51.655,0],[0,51.655],[-51.655,0],[0,-51.655]],"v":[[0,-93.529],[93.529,0],[0,93.529],[-93.529,0]],"c":true}]},{"i":{"x":0.667,"y":1},"o":{"x":0.333,"y":0},"t":13,"s":[{"i":[[-51.655,0],[0,-51.655],[51.655,0],[0,51.655]],"o":[[51.655,0],[0,51.655],[-51.655,0],[0,-51.655]],"v":[[-7.725,-144.952],[85.804,-51.423],[-7.725,42.106],[-101.255,-51.423]],"c":true}]},{"i":{"x":0.667,"y":1},"o":{"x":0.333,"y":0},"t":23,"s":[{"i":[[-51.655,0],[0,-51.655],[51.655,0],[0,51.655]],"o":[[51.655,0],[0,51.655],[-51.655,0],[0,-51.655]],"v":[[-7.725,-144.952],[85.804,-51.423],[-7.725,42.106],[-101.255,-51.423]],"c":true}]},{"i":{"x":0.667,"y":1},"o":{"x":0.333,"y":0},"t":33,"s":[{"i":[[-51.655,0],[0,-51.655],[51.655,0],[0,51.655]],"o":[[51.655,0],[0,51.655],[-51.655,0],[0,-51.655]],"v":[[0,-117.529],[93.529,-24],[0,69.529],[-93.529,-24]],"c":true}]},{"t":43,"s":[{"i":[[-51.655,0],[0,-51.655],[51.655,0],[0,51.655]],"o":[[51.655,0],[0,51.655],[-51.655,0],[0,-51.655]],"v":[[0,-93.529],[93.529,0],[0,93.529],[-93.529,0]],"c":true}]}],"ix":2},"nm":"Path 1","mn":"ADBE Vector Shape - Group","hd":false},{"ty":"st","c":{"a":0,"k":[0,0,0,1],"ix":3},"o":{"a":0,"k":100,"ix":4},"w":{"a":0,"k":18,"ix":5},"lc":2,"lj":2,"bm":0,"nm":"Stroke 1","mn":"ADBE Vector Graphic - Stroke","hd":false},{"ty":"tr","p":{"a":0,"k":[375,375],"ix":2},"a":{"a":0,"k":[0,0],"ix":1},"s":{"a":0,"k":[100,100],"ix":3},"r":{"a":0,"k":0,"ix":6},"o":{"a":0,"k":100,"ix":7},"sk":{"a":0,"k":0,"ix":4},"sa":{"a":0,"k":0,"ix":5},"nm":"Transform"}],"nm":"Group 2","np":2,"cix":2,"bm":0,"ix":2,"mn":"ADBE Vector Group","hd":false},{"ty":"tr","p":{"a":0,"k":[375,375],"ix":2},"a":{"a":0,"k":[375,375],"ix":1},"s":{"a":0,"k":[100,100],"ix":3},"r":{"a":1,"k":[{"i":{"x":[0.3],"y":[1]},"o":{"x":[0.7],"y":[0]},"t":0,"s":[0]},{"t":60,"s":[360]}],"ix":6},"o":{"a":0,"k":100,"ix":7},"sk":{"a":0,"k":0,"ix":4},"sa":{"a":0,"k":0,"ix":5},"nm":"Transform"}],"nm":"Group 1","np":2,"cix":2,"bm":0,"ix":1,"mn":"ADBE Vector Group","hd":false},{"ty":"gr","it":[{"ind":0,"ty":"sh","ix":1,"ks":{"a":1,"k":[{"i":{"x":0.667,"y":1},"o":{"x":0.333,"y":0},"t":3,"s":[{"i":[[0,0],[79.595,-23.979]],"o":[[0,0],[0,0]],"v":[[71.37,-40.251],[-71.37,40.251]],"c":false}]},{"i":{"x":0.667,"y":1},"o":{"x":0.333,"y":0},"t":13,"s":[{"i":[[0,0],[79.595,-23.979]],"o":[[0,0],[0,0]],"v":[[71.37,-92.251],[-71.37,-11.749]],"c":false}]},{"i":{"x":0.667,"y":1},"o":{"x":0.333,"y":0},"t":23,"s":[{"i":[[0,0],[79.595,-23.979]],"o":[[0,0],[0,0]],"v":[[71.37,-92.251],[-71.37,-11.749]],"c":false}]},{"i":{"x":0.667,"y":1},"o":{"x":0.333,"y":0},"t":33,"s":[{"i":[[0,0],[79.595,-23.979]],"o":[[0,0],[0,0]],"v":[[71.37,-16.251],[-71.37,64.251]],"c":false}]},{"t":43,"s":[{"i":[[0,0],[79.595,-23.979]],"o":[[0,0],[0,0]],"v":[[71.37,-40.251],[-71.37,40.251]],"c":false}]}],"ix":2},"nm":"Path 1","mn":"ADBE Vector Shape - Group","hd":false},{"ty":"st","c":{"a":0,"k":[0,0,0,1],"ix":3},"o":{"a":0,"k":100,"ix":4},"w":{"a":0,"k":18,"ix":5},"lc":2,"lj":2,"bm":0,"nm":"Stroke 1","mn":"ADBE Vector Graphic - Stroke","hd":false},{"ty":"tr","p":{"a":0,"k":[539.899,324.373],"ix":2},"a":{"a":0,"k":[0,0],"ix":1},"s":{"a":0,"k":[100,100],"ix":3},"r":{"a":0,"k":0,"ix":6},"o":{"a":0,"k":100,"ix":7},"sk":{"a":0,"k":0,"ix":4},"sa":{"a":0,"k":0,"ix":5},"nm":"Transform"}],"nm":"Group 2","np":2,"cix":2,"bm":0,"ix":2,"mn":"ADBE Vector Group","hd":false},{"ty":"gr","it":[{"ind":0,"ty":"sh","ix":1,"ks":{"a":1,"k":[{"i":{"x":0.667,"y":1},"o":{"x":0.333,"y":0},"t":3,"s":[{"i":[[0,0],[-77.787,-24.599]],"o":[[0,0],[0,0]],"v":[[-69.461,-39.662],[69.461,39.662]],"c":false}]},{"i":{"x":0.667,"y":1},"o":{"x":0.333,"y":0},"t":13,"s":[{"i":[[0,0],[-77.787,-24.599]],"o":[[0,0],[0,0]],"v":[[-69.461,-91.662],[69.461,-12.338]],"c":false}]},{"i":{"x":0.667,"y":1},"o":{"x":0.333,"y":0},"t":23,"s":[{"i":[[0,0],[-77.787,-24.599]],"o":[[0,0],[0,0]],"v":[[-69.461,-91.662],[69.461,-12.338]],"c":false}]},{"i":{"x":0.667,"y":1},"o":{"x":0.333,"y":0},"t":33,"s":[{"i":[[0,0],[-77.787,-24.599]],"o":[[0,0],[0,0]],"v":[[-69.461,-15.662],[69.461,63.662]],"c":false}]},{"t":43,"s":[{"i":[[0,0],[-77.787,-24.599]],"o":[[0,0],[0,0]],"v":[[-69.461,-39.662],[69.461,39.662]],"c":false}]}],"ix":2},"nm":"Path 1","mn":"ADBE Vector Shape - Group","hd":false},{"ty":"st","c":{"a":0,"k":[0,0,0,1],"ix":3},"o":{"a":0,"k":100,"ix":4},"w":{"a":0,"k":18,"ix":5},"lc":2,"lj":2,"bm":0,"nm":"Stroke 1","mn":"ADBE Vector Graphic - Stroke","hd":false},{"ty":"tr","p":{"a":0,"k":[208.192,323.784],"ix":2},"a":{"a":0,"k":[0,0],"ix":1},"s":{"a":0,"k":[100,100],"ix":3},"r":{"a":0,"k":0,"ix":6},"o":{"a":0,"k":100,"ix":7},"sk":{"a":0,"k":0,"ix":4},"sa":{"a":0,"k":0,"ix":5},"nm":"Transform"}],"nm":"Group 3","np":2,"cix":2,"bm":0,"ix":3,"mn":"ADBE Vector Group","hd":false},{"ty":"tr","p":{"a":0,"k":[375,375],"ix":2},"a":{"a":0,"k":[375,375],"ix":1},"s":{"a":0,"k":[100,100],"ix":3},"r":{"a":0,"k":0,"ix":6},"o":{"a":0,"k":100,"ix":7},"sk":{"a":0,"k":0,"ix":4},"sa":{"a":0,"k":0,"ix":5},"nm":"Transform"}],"nm":"Group 6","np":3,"cix":2,"bm":0,"ix":1,"mn":"ADBE Vector Group","hd":false},{"ty":"gr","it":[{"ty":"gr","it":[{"ind":0,"ty":"sh","ix":1,"ks":{"a":1,"k":[{"i":{"x":0.667,"y":1},"o":{"x":0.333,"y":0},"t":0,"s":[{"i":[[0,0],[0,0],[-23.238,0],[0,0],[0,-20.564],[0,0]],"o":[[0,0],[0,-20.564],[0,0],[23.238,0],[0,0],[0,0]],"v":[[-87.941,38.118],[-87.941,-0.882],[-45.865,-38.118],[45.865,-38.118],[87.941,-0.882],[87.941,38.118]],"c":false}]},{"i":{"x":0.667,"y":1},"o":{"x":0.333,"y":0},"t":10,"s":[{"i":[[0,0],[0,0],[-23.238,0],[0,0],[0,-20.564],[0,0]],"o":[[0,0],[0,-20.564],[0,0],[23.238,0],[0,0],[0,0]],"v":[[-87.941,-13.882],[-87.941,-52.882],[-45.865,-90.118],[45.865,-90.118],[87.941,-52.882],[87.941,-13.882]],"c":false}]},{"i":{"x":0.667,"y":1},"o":{"x":0.333,"y":0},"t":20,"s":[{"i":[[0,0],[0,0],[-23.238,0],[0,0],[0,-20.564],[0,0]],"o":[[0,0],[0,-20.564],[0,0],[23.238,0],[0,0],[0,0]],"v":[[-87.941,-13.882],[-87.941,-52.882],[-45.865,-90.118],[45.865,-90.118],[87.941,-52.882],[87.941,-13.882]],"c":false}]},{"i":{"x":0.667,"y":1},"o":{"x":0.333,"y":0},"t":30,"s":[{"i":[[0,0],[0,0],[-23.238,0],[0,0],[0,-20.564],[0,0]],"o":[[0,0],[0,-20.564],[0,0],[23.238,0],[0,0],[0,0]],"v":[[-87.941,62.118],[-87.941,23.118],[-45.865,-14.118],[45.865,-14.118],[87.941,23.118],[87.941,62.118]],"c":false}]},{"t":40,"s":[{"i":[[0,0],[0,0],[-23.238,0],[0,0],[0,-20.564],[0,0]],"o":[[0,0],[0,-20.564],[0,0],[23.238,0],[0,0],[0,0]],"v":[[-87.941,38.118],[-87.941,-0.882],[-45.865,-38.118],[45.865,-38.118],[87.941,-0.882],[87.941,38.118]],"c":false}]}],"ix":2},"nm":"Path 1","mn":"ADBE Vector Shape - Group","hd":false},{"ty":"st","c":{"a":0,"k":[0,0,0,1],"ix":3},"o":{"a":0,"k":100,"ix":4},"w":{"a":0,"k":18,"ix":5},"lc":2,"lj":2,"bm":0,"nm":"Stroke 1","mn":"ADBE Vector Graphic - Stroke","hd":false},{"ty":"tr","p":{"a":0,"k":[375,155.794],"ix":2},"a":{"a":0,"k":[0,0],"ix":1},"s":{"a":0,"k":[100,100],"ix":3},"r":{"a":0,"k":0,"ix":6},"o":{"a":0,"k":100,"ix":7},"sk":{"a":0,"k":0,"ix":4},"sa":{"a":0,"k":0,"ix":5},"nm":"Transform"}],"nm":"Group 4","np":2,"cix":2,"bm":0,"ix":1,"mn":"ADBE Vector Group","hd":false},{"ty":"gr","it":[{"ind":0,"ty":"sh","ix":1,"ks":{"a":1,"k":[{"i":{"x":0.667,"y":1},"o":{"x":0.333,"y":0},"t":0,"s":[{"i":[[40.393,0],[0,0],[3.352,37.953],[0,0],[-48.041,0],[0,0],[4.334,-49.081],[0,0]],"o":[[0,0],[-40.393,0],[0,0],[-4.334,-49.081],[0,0],[48.041,0],[0,0],[-3.352,37.953]],"v":[[132.216,220.147],[-132.216,220.147],[-211.345,152.3],[-236.269,-129.937],[-157.25,-220.147],[157.25,-220.147],[236.269,-129.937],[211.344,152.3]],"c":true}]},{"i":{"x":0.667,"y":1},"o":{"x":0.333,"y":0},"t":10,"s":[{"i":[[40.393,0],[0,0],[3.352,37.953],[0,0],[-48.041,0],[0,0],[4.334,-49.081],[0,0]],"o":[[0,0],[-40.393,0],[0,0],[-4.334,-49.081],[0,0],[48.041,0],[0,0],[-3.352,37.953]],"v":[[132.216,168.147],[-132.216,168.147],[-211.345,100.3],[-236.269,-181.937],[-157.25,-272.147],[157.25,-272.147],[236.269,-181.937],[211.345,100.3]],"c":true}]},{"i":{"x":0.667,"y":1},"o":{"x":0.333,"y":0},"t":20,"s":[{"i":[[40.393,0],[0,0],[3.352,37.953],[0,0],[-48.041,0],[0,0],[4.334,-49.081],[0,0]],"o":[[0,0],[-40.393,0],[0,0],[-4.334,-49.081],[0,0],[48.041,0],[0,0],[-3.352,37.953]],"v":[[132.216,168.147],[-132.216,168.147],[-211.345,100.3],[-236.269,-181.937],[-157.25,-272.147],[157.25,-272.147],[236.269,-181.937],[211.345,100.3]],"c":true}]},{"i":{"x":0.667,"y":1},"o":{"x":0.333,"y":0},"t":30,"s":[{"i":[[40.393,0],[0,0],[3.352,37.953],[0,0],[-48.041,0],[0,0],[4.334,-49.081],[0,0]],"o":[[0,0],[-40.393,0],[0,0],[-4.334,-49.081],[0,0],[48.041,0],[0,0],[-3.352,37.953]],"v":[[132.216,244.147],[-132.216,244.147],[-211.345,176.3],[-236.269,-105.937],[-157.25,-196.147],[157.25,-196.147],[236.269,-105.937],[211.344,176.3]],"c":true}]},{"t":40,"s":[{"i":[[40.393,0],[0,0],[3.352,37.953],[0,0],[-48.041,0],[0,0],[4.334,-49.081],[0,0]],"o":[[0,0],[-40.393,0],[0,0],[-4.334,-49.081],[0,0],[48.041,0],[0,0],[-3.352,37.953]],"v":[[132.216,220.147],[-132.216,220.147],[-211.345,152.3],[-236.269,-129.937],[-157.25,-220.147],[157.25,-220.147],[236.269,-129.937],[211.344,152.3]],"c":true}]}],"ix":2},"nm":"Path 1","mn":"ADBE Vector Shape - Group","hd":false},{"ty":"st","c":{"a":0,"k":[0,0,0,1],"ix":3},"o":{"a":0,"k":100,"ix":4},"w":{"a":0,"k":18,"ix":5},"lc":2,"lj":2,"bm":0,"nm":"Stroke 1","mn":"ADBE Vector Graphic - Stroke","hd":false},{"ty":"tr","p":{"a":0,"k":[375,414.059],"ix":2},"a":{"a":0,"k":[0,0],"ix":1},"s":{"a":0,"k":[100,100],"ix":3},"r":{"a":0,"k":0,"ix":6},"o":{"a":0,"k":100,"ix":7},"sk":{"a":0,"k":0,"ix":4},"sa":{"a":0,"k":0,"ix":5},"nm":"Transform"}],"nm":"Group 5","np":2,"cix":2,"bm":0,"ix":2,"mn":"ADBE Vector Group","hd":false},{"ty":"tr","p":{"a":0,"k":[375,375.941],"ix":2},"a":{"a":0,"k":[375,375.941],"ix":1},"s":{"a":0,"k":[100,100],"ix":3},"r":{"a":0,"k":0,"ix":6},"o":{"a":0,"k":100,"ix":7},"sk":{"a":0,"k":0,"ix":4},"sa":{"a":0,"k":0,"ix":5},"nm":"Transform"}],"nm":"Group 7","np":2,"cix":2,"bm":0,"ix":2,"mn":"ADBE Vector Group","hd":false}],"ip":0,"op":180,"st":0,"ct":1,"bm":0}],"markers":[]}