{"v":"5.9.6","fr":60,"ip":0,"op":120,"w":750,"h":750,"nm":"Main render","ddd":0,"assets":[],"layers":[{"ddd":0,"ind":1,"ty":4,"nm":"Layer 3","sr":1,"ks":{"o":{"a":0,"k":40,"ix":11},"r":{"a":0,"k":0,"ix":10},"p":{"a":0,"k":[598.378,505.037,0],"ix":2,"l":2},"a":{"a":0,"k":[598.378,505.037,0],"ix":1,"l":2},"s":{"a":0,"k":[100,100,100],"ix":6,"l":2}},"ao":0,"shapes":[{"ty":"gr","it":[{"ind":0,"ty":"sh","ix":1,"ks":{"a":1,"k":[{"i":{"x":0.667,"y":1},"o":{"x":0.333,"y":0},"t":32,"s":[{"i":[[0,0],[0,0],[0,0]],"o":[[0,0],[0,0],[0,0]],"v":[[-0.884,11.062],[1.279,12.768],[2.738,12.768]],"c":false}]},{"i":{"x":0.667,"y":1},"o":{"x":0.333,"y":0},"t":42,"s":[{"i":[[0,0],[0,0],[0,0]],"o":[[0,0],[0,0],[0,0]],"v":[[-32.038,-16.656],[5.279,12.768],[30.43,12.768]],"c":false}]},{"t":52,"s":[{"i":[[0,0],[0,0],[0,0]],"o":[[0,0],[0,0],[0,0]],"v":[[-27.107,-12.768],[5.28,12.768],[27.107,12.768]],"c":false}]}],"ix":2},"nm":"Path 1","mn":"ADBE Vector Shape - Group","hd":false},{"ty":"st","c":{"a":0,"k":[0,0,0,1],"ix":3},"o":{"a":0,"k":100,"ix":4},"w":{"a":0,"k":35,"ix":5},"lc":2,"lj":2,"bm":0,"nm":"Stroke 1","mn":"ADBE Vector Graphic - Stroke","hd":false},{"ty":"tr","p":{"a":0,"k":[593.099,492.269],"ix":2},"a":{"a":0,"k":[0,0],"ix":1},"s":{"a":0,"k":[100,100],"ix":3},"r":{"a":0,"k":0,"ix":6},"o":{"a":0,"k":100,"ix":7},"sk":{"a":0,"k":0,"ix":4},"sa":{"a":0,"k":0,"ix":5},"nm":"Transform"}],"nm":"Group 1","np":2,"cix":2,"bm":0,"ix":1,"mn":"ADBE Vector Group","hd":false},{"ty":"gr","it":[{"ind":0,"ty":"sh","ix":1,"ks":{"a":1,"k":[{"i":{"x":0.667,"y":1},"o":{"x":0.333,"y":0},"t":32,"s":[{"i":[[-3.105,0],[0,-3.105],[3.105,0],[0,3.105]],"o":[[3.105,0],[0,3.105],[-3.105,0],[0,-3.105]],"v":[[-4,-5.622],[1.622,0],[-4,5.622],[-9.622,0]],"c":true}]},{"i":{"x":0.667,"y":1},"o":{"x":0.333,"y":0},"t":42,"s":[{"i":[[-53.551,0],[0,-53.551],[53.551,0],[0,53.551]],"o":[[53.551,0],[0,53.551],[-53.551,0],[0,-53.551]],"v":[[0,-96.963],[96.963,0],[0,96.963],[-96.963,0]],"c":true}]},{"t":52,"s":[{"i":[[-46.475,0],[0,-46.475],[46.475,0],[0,46.475]],"o":[[46.475,0],[0,46.475],[-46.475,0],[0,-46.475]],"v":[[0,-84.151],[84.151,0],[0,84.151],[-84.151,0]],"c":true}]}],"ix":2},"nm":"Path 1","mn":"ADBE Vector Shape - Group","hd":false},{"ty":"st","c":{"a":0,"k":[0,0,0,1],"ix":3},"o":{"a":0,"k":100,"ix":4},"w":{"a":0,"k":35,"ix":5},"lc":2,"lj":2,"bm":0,"nm":"Stroke 1","mn":"ADBE Vector Graphic - Stroke","hd":false},{"ty":"tr","p":{"a":0,"k":[598.378,505.037],"ix":2},"a":{"a":0,"k":[0,0],"ix":1},"s":{"a":0,"k":[100,100],"ix":3},"r":{"a":0,"k":0,"ix":6},"o":{"a":0,"k":100,"ix":7},"sk":{"a":0,"k":0,"ix":4},"sa":{"a":0,"k":0,"ix":5},"nm":"Transform"}],"nm":"Group 2","np":2,"cix":2,"bm":0,"ix":2,"mn":"ADBE Vector Group","hd":false}],"ip":32,"op":212,"st":32,"ct":1,"bm":0},{"ddd":0,"ind":2,"ty":4,"nm":"Layer 1","sr":1,"ks":{"o":{"a":0,"k":40,"ix":11},"r":{"a":0,"k":0,"ix":10},"p":{"a":0,"k":[598.378,505.037,0],"ix":2,"l":2},"a":{"a":0,"k":[598.378,505.037,0],"ix":1,"l":2},"s":{"a":0,"k":[100,100,100],"ix":6,"l":2}},"ao":0,"shapes":[{"ty":"gr","it":[{"ind":0,"ty":"sh","ix":1,"ks":{"a":1,"k":[{"i":{"x":0.667,"y":1},"o":{"x":0.333,"y":0},"t":0,"s":[{"i":[[0,0],[0,0],[0,0]],"o":[[0,0],[0,0],[0,0]],"v":[[-27.107,-12.768],[5.28,12.768],[27.107,12.768]],"c":false}]},{"t":10,"s":[{"i":[[0,0],[0,0],[0,0]],"o":[[0,0],[0,0],[0,0]],"v":[[-0.884,11.062],[1.279,12.768],[2.738,12.768]],"c":false}]}],"ix":2},"nm":"Path 1","mn":"ADBE Vector Shape - Group","hd":false},{"ty":"st","c":{"a":0,"k":[0,0,0,1],"ix":3},"o":{"a":0,"k":100,"ix":4},"w":{"a":0,"k":35,"ix":5},"lc":2,"lj":2,"bm":0,"nm":"Stroke 1","mn":"ADBE Vector Graphic - Stroke","hd":false},{"ty":"tr","p":{"a":0,"k":[593.099,492.269],"ix":2},"a":{"a":0,"k":[0,0],"ix":1},"s":{"a":0,"k":[100,100],"ix":3},"r":{"a":0,"k":0,"ix":6},"o":{"a":0,"k":100,"ix":7},"sk":{"a":0,"k":0,"ix":4},"sa":{"a":0,"k":0,"ix":5},"nm":"Transform"}],"nm":"Group 1","np":2,"cix":2,"bm":0,"ix":1,"mn":"ADBE Vector Group","hd":false},{"ty":"gr","it":[{"ind":0,"ty":"sh","ix":1,"ks":{"a":1,"k":[{"i":{"x":0.667,"y":1},"o":{"x":0.333,"y":0},"t":0,"s":[{"i":[[-46.475,0],[0,-46.475],[46.475,0],[0,46.475]],"o":[[46.475,0],[0,46.475],[-46.475,0],[0,-46.475]],"v":[[0,-84.151],[84.151,0],[0,84.151],[-84.151,0]],"c":true}]},{"t":10,"s":[{"i":[[-3.105,0],[0,-3.105],[3.105,0],[0,3.105]],"o":[[3.105,0],[0,3.105],[-3.105,0],[0,-3.105]],"v":[[-4,-5.622],[1.622,0],[-4,5.622],[-9.622,0]],"c":true}]}],"ix":2},"nm":"Path 1","mn":"ADBE Vector Shape - Group","hd":false},{"ty":"st","c":{"a":0,"k":[0,0,0,1],"ix":3},"o":{"a":0,"k":100,"ix":4},"w":{"a":0,"k":35,"ix":5},"lc":2,"lj":2,"bm":0,"nm":"Stroke 1","mn":"ADBE Vector Graphic - Stroke","hd":false},{"ty":"tr","p":{"a":0,"k":[598.378,505.037],"ix":2},"a":{"a":0,"k":[0,0],"ix":1},"s":{"a":0,"k":[100,100],"ix":3},"r":{"a":0,"k":0,"ix":6},"o":{"a":0,"k":100,"ix":7},"sk":{"a":0,"k":0,"ix":4},"sa":{"a":0,"k":0,"ix":5},"nm":"Transform"}],"nm":"Group 2","np":2,"cix":2,"bm":0,"ix":2,"mn":"ADBE Vector Group","hd":false}],"ip":0,"op":10,"st":0,"ct":1,"bm":0},{"ddd":0,"ind":3,"ty":4,"nm":"Layer 2","sr":1,"ks":{"o":{"a":0,"k":100,"ix":11},"r":{"a":0,"k":0,"ix":10},"p":{"a":0,"k":[375,375,0],"ix":2,"l":2},"a":{"a":0,"k":[375,375,0],"ix":1,"l":2},"s":{"a":0,"k":[100,100,100],"ix":6,"l":2}},"ao":0,"shapes":[{"ty":"gr","it":[{"ind":0,"ty":"sh","ix":1,"ks":{"a":1,"k":[{"i":{"x":0.29,"y":1},"o":{"x":0.71,"y":0},"t":6,"s":[{"i":[[0,0],[0,0]],"o":[[0,0],[0,0]],"v":[[0,-130.037],[0,130.037]],"c":false}]},{"i":{"x":0.29,"y":1},"o":{"x":0.71,"y":0},"t":18,"s":[{"i":[[0,0],[0,0]],"o":[[0,0],[0,0]],"v":[[-132.027,-280.219],[-132.36,64.613]],"c":false}]},{"i":{"x":0.667,"y":1},"o":{"x":0.71,"y":0},"t":22,"s":[{"i":[[0,0],[0,0]],"o":[[0,0],[0,0]],"v":[[-132.027,-280.219],[-132.36,64.613]],"c":false}]},{"i":{"x":0.667,"y":1},"o":{"x":0.333,"y":0},"t":32,"s":[{"i":[[0,0],[0,0]],"o":[[0,0],[0,0]],"v":[[0,-130.037],[0,152.494]],"c":false}]},{"i":{"x":0.667,"y":1},"o":{"x":0.333,"y":0},"t":42,"s":[{"i":[[0,0],[0,0]],"o":[[0,0],[0,0]],"v":[[0,-130.037],[0,113.171]],"c":false}]},{"t":52,"s":[{"i":[[0,0],[0,0]],"o":[[0,0],[0,0]],"v":[[0,-130.037],[0,130.037]],"c":false}]}],"ix":2},"nm":"Path 1","mn":"ADBE Vector Shape - Group","hd":false},{"ty":"st","c":{"a":0,"k":[0,0,0,1],"ix":3},"o":{"a":0,"k":100,"ix":4},"w":{"a":0,"k":35,"ix":5},"lc":2,"lj":2,"bm":0,"nm":"Stroke 1","mn":"ADBE Vector Graphic - Stroke","hd":false},{"ty":"tr","p":{"a":0,"k":[375,505.037],"ix":2},"a":{"a":0,"k":[0,0],"ix":1},"s":{"a":0,"k":[100,100],"ix":3},"r":{"a":0,"k":0,"ix":6},"o":{"a":0,"k":100,"ix":7},"sk":{"a":0,"k":0,"ix":4},"sa":{"a":0,"k":0,"ix":5},"nm":"Transform"}],"nm":"Group 1","np":2,"cix":2,"bm":0,"ix":1,"mn":"ADBE Vector Group","hd":false},{"ty":"gr","it":[{"ind":0,"ty":"sh","ix":1,"ks":{"a":1,"k":[{"i":{"x":0.29,"y":1},"o":{"x":0.71,"y":0},"t":6,"s":[{"i":[[0,0],[0,0],[0,0]],"o":[[0,0],[0,0],[0,0]],"v":[[-225.231,-65.019],[0,65.019],[225.231,-65.019]],"c":false}]},{"i":{"x":0.29,"y":1},"o":{"x":0.71,"y":0},"t":18,"s":[{"i":[[0,0],[0,0],[0,0]],"o":[[0,0],[0,0],[0,0]],"v":[[-131.995,-88.543],[-132.027,-85.163],[140.406,-88.543]],"c":false}]},{"i":{"x":0.667,"y":1},"o":{"x":0.71,"y":0},"t":22,"s":[{"i":[[0,0],[0,0],[0,0]],"o":[[0,0],[0,0],[0,0]],"v":[[-131.995,-88.543],[-132.027,-85.163],[140.406,-88.543]],"c":false}]},{"i":{"x":0.667,"y":1},"o":{"x":0.333,"y":0},"t":32,"s":[{"i":[[0,0],[0,0],[0,0]],"o":[[0,0],[0,0],[0,0]],"v":[[-244.679,-76.247],[0,65.019],[244.679,-76.247]],"c":false}]},{"i":{"x":0.667,"y":1},"o":{"x":0.333,"y":0},"t":42,"s":[{"i":[[0,0],[0,0],[0,0]],"o":[[0,0],[0,0],[0,0]],"v":[[-210.624,-56.585],[0,65.019],[210.624,-56.585]],"c":false}]},{"t":52,"s":[{"i":[[0,0],[0,0],[0,0]],"o":[[0,0],[0,0],[0,0]],"v":[[-225.231,-65.019],[0,65.019],[225.231,-65.019]],"c":false}]}],"ix":2},"nm":"Path 1","mn":"ADBE Vector Shape - Group","hd":false},{"ty":"st","c":{"a":0,"k":[0,0,0,1],"ix":3},"o":{"a":0,"k":100,"ix":4},"w":{"a":0,"k":35,"ix":5},"lc":2,"lj":2,"bm":0,"nm":"Stroke 1","mn":"ADBE Vector Graphic - Stroke","hd":false},{"ty":"tr","p":{"a":0,"k":[375,309.981],"ix":2},"a":{"a":0,"k":[0,0],"ix":1},"s":{"a":0,"k":[100,100],"ix":3},"r":{"a":0,"k":0,"ix":6},"o":{"a":0,"k":100,"ix":7},"sk":{"a":0,"k":0,"ix":4},"sa":{"a":0,"k":0,"ix":5},"nm":"Transform"}],"nm":"Group 2","np":2,"cix":2,"bm":0,"ix":2,"mn":"ADBE Vector Group","hd":false},{"ty":"gr","it":[{"ind":0,"ty":"sh","ix":1,"ks":{"a":1,"k":[{"i":{"x":0.29,"y":1},"o":{"x":0.71,"y":0},"t":6,"s":[{"i":[[0,18.181],[0,0],[15.745,9.09],[0,0],[15.745,-9.09],[0,0],[0,-18.181],[0,0],[-15.745,-9.09],[0,0],[-15.745,9.09],[0,0]],"o":[[0,0],[0,-18.181],[0,0],[-15.745,-9.09],[0,0],[-15.745,9.09],[0,0],[0,18.181],[0,0],[15.745,9.09],[0,0],[15.745,-9.09]],"v":[[232.049,104.593],[232.049,-104.593],[206.605,-148.664],[25.444,-253.257],[-25.444,-253.257],[-206.605,-148.664],[-232.049,-104.593],[-232.049,104.593],[-206.605,148.664],[-25.444,253.257],[25.444,253.257],[206.605,148.664]],"c":true}]},{"i":{"x":0.29,"y":1},"o":{"x":0.71,"y":0},"t":18,"s":[{"i":[[2.594,76.919],[0,0],[21.47,0.236],[0,0],[-0.234,-0.236],[0,0],[0,-0.473],[0,0],[-0.204,-12.396],[0,0],[-0.204,-0.691],[0,0]],"o":[[0,0],[0,-0.473],[0,0],[0.234,-0.236],[0,0],[0.002,0.236],[0,0],[0,24.792],[0,0],[0.204,-0.691],[0,0],[31.836,-1.587]],"v":[[149.77,126.081],[149.703,-152.9],[115.006,-154.045],[-132.031,-156.764],[-131.273,-156.764],[-131.998,-154.045],[-131.994,-152.9],[-135.364,-7.555],[-135.034,52.542],[-132.689,195.168],[-132.031,195.168],[115.073,186.178]],"c":true}]},{"i":{"x":0.667,"y":1},"o":{"x":0.71,"y":0},"t":22,"s":[{"i":[[2.594,76.919],[0,0],[21.47,0.236],[0,0],[-0.234,-0.236],[0,0],[0,-0.473],[0,0],[-0.204,-12.396],[0,0],[-0.204,-0.691],[0,0]],"o":[[0,0],[0,-0.473],[0,0],[0.234,-0.236],[0,0],[0.002,0.236],[0,0],[0,24.792],[0,0],[0.204,-0.691],[0,0],[31.836,-1.587]],"v":[[149.77,126.081],[149.703,-152.9],[115.006,-154.045],[-132.031,-156.764],[-131.273,-156.764],[-131.998,-154.045],[-131.994,-152.9],[-135.364,-7.555],[-135.034,52.542],[-132.689,195.168],[-132.031,195.168],[115.073,186.178]],"c":true}]},{"i":{"x":0.667,"y":1},"o":{"x":0.333,"y":0},"t":32,"s":[{"i":[[0,19.751],[0,0],[17.104,9.875],[0,0],[17.104,-9.875],[0,0],[0,-19.751],[0,0],[-17.105,-9.875],[0,0],[-17.104,9.875],[0,0]],"o":[[0,0],[0,-19.751],[0,0],[-17.104,-9.875],[0,0],[-17.105,9.875],[0,0],[0,19.751],[0,0],[17.104,9.875],[0,0],[17.104,-9.875]],"v":[[252.086,113.624],[252.086,-113.624],[224.444,-161.5],[27.641,-275.125],[-27.641,-275.125],[-224.444,-161.5],[-252.086,-113.624],[-252.086,113.624],[-224.444,161.5],[-27.641,275.125],[27.641,275.125],[224.444,161.5]],"c":true}]},{"i":{"x":0.667,"y":1},"o":{"x":0.333,"y":0},"t":42,"s":[{"i":[[0,17.002],[0,0],[14.724,8.501],[0,0],[14.724,-8.501],[0,0],[0,-17.002],[0,0],[-14.724,-8.501],[0,0],[-14.724,8.501],[0,0]],"o":[[0,0],[0,-17.002],[0,0],[-14.724,-8.501],[0,0],[-14.724,8.501],[0,0],[0,17.002],[0,0],[14.724,8.501],[0,0],[14.724,-8.501]],"v":[[217,97.81],[217,-97.81],[193.206,-139.023],[23.794,-236.832],[-23.794,-236.832],[-193.206,-139.023],[-217,-97.81],[-217,97.81],[-193.206,139.023],[-23.794,236.832],[23.794,236.832],[193.206,139.023]],"c":true}]},{"t":52,"s":[{"i":[[0,18.181],[0,0],[15.745,9.09],[0,0],[15.745,-9.09],[0,0],[0,-18.181],[0,0],[-15.745,-9.09],[0,0],[-15.745,9.09],[0,0]],"o":[[0,0],[0,-18.181],[0,0],[-15.745,-9.09],[0,0],[-15.745,9.09],[0,0],[0,18.181],[0,0],[15.745,9.09],[0,0],[15.745,-9.09]],"v":[[232.049,104.593],[232.049,-104.593],[206.605,-148.664],[25.444,-253.257],[-25.444,-253.257],[-206.605,-148.664],[-232.049,-104.593],[-232.049,104.593],[-206.605,148.664],[-25.444,253.257],[25.444,253.257],[206.605,148.664]],"c":true}]}],"ix":2},"nm":"Path 1","mn":"ADBE Vector Shape - Group","hd":false},{"ty":"st","c":{"a":0,"k":[0,0,0,1],"ix":3},"o":{"a":0,"k":100,"ix":4},"w":{"a":0,"k":35,"ix":5},"lc":2,"lj":2,"bm":0,"nm":"Stroke 1","mn":"ADBE Vector Graphic - Stroke","hd":false},{"ty":"tm","s":{"a":1,"k":[{"i":{"x":[0.667],"y":[1]},"o":{"x":[0.333],"y":[0]},"t":0,"s":[6]},{"i":{"x":[0.667],"y":[1]},"o":{"x":[0.333],"y":[0]},"t":10,"s":[0]},{"i":{"x":[0.667],"y":[1]},"o":{"x":[0.333],"y":[0]},"t":32,"s":[0]},{"t":42,"s":[6]}],"ix":1},"e":{"a":1,"k":[{"i":{"x":[0.667],"y":[1]},"o":{"x":[0.333],"y":[0]},"t":0,"s":[94]},{"i":{"x":[0.667],"y":[1]},"o":{"x":[0.333],"y":[0]},"t":10,"s":[100]},{"i":{"x":[0.667],"y":[1]},"o":{"x":[0.333],"y":[0]},"t":32,"s":[100]},{"t":42,"s":[94]}],"ix":2},"o":{"a":0,"k":-7,"ix":3},"m":1,"ix":3,"nm":"Trim Paths 1","mn":"ADBE Vector Filter - Trim","hd":false},{"ty":"tr","p":{"a":0,"k":[375,375],"ix":2},"a":{"a":0,"k":[0,0],"ix":1},"s":{"a":0,"k":[100,100],"ix":3},"r":{"a":0,"k":0,"ix":6},"o":{"a":0,"k":100,"ix":7},"sk":{"a":0,"k":0,"ix":4},"sa":{"a":0,"k":0,"ix":5},"nm":"Transform"}],"nm":"Group 3","np":3,"cix":2,"bm":0,"ix":3,"mn":"ADBE Vector Group","hd":false}],"ip":0,"op":180,"st":0,"ct":1,"bm":0}],"markers":[]}