{"v":"5.9.6","fr":60,"ip":0,"op":120,"w":750,"h":750,"nm":"Main render","ddd":0,"assets":[],"layers":[{"ddd":0,"ind":1,"ty":4,"nm":"Layer 1","sr":1,"ks":{"o":{"a":0,"k":100,"ix":11},"r":{"a":0,"k":0,"ix":10},"p":{"a":0,"k":[375,375,0],"ix":2,"l":2},"a":{"a":0,"k":[375,375,0],"ix":1,"l":2},"s":{"a":0,"k":[100,100,100],"ix":6,"l":2}},"ao":0,"shapes":[{"ty":"gr","it":[{"ty":"gr","it":[{"ind":0,"ty":"sh","ix":1,"ks":{"a":1,"k":[{"i":{"x":0.667,"y":1},"o":{"x":0.333,"y":0},"t":0,"s":[{"i":[[17.262,0],[0,0],[0,17.262],[0,0],[-17.262,0],[0,0],[0,-17.262],[0,0]],"o":[[0,0],[-17.262,0],[0,0],[0,-17.262],[0,0],[17.262,0],[0,0],[0,17.262]],"v":[[30.004,61.26],[-30.004,61.26],[-61.26,30.004],[-61.26,-30.004],[-30.004,-61.26],[30.004,-61.26],[61.26,-30.004],[61.26,30.004]],"c":true}]},{"i":{"x":0.667,"y":1},"o":{"x":0.333,"y":0},"t":10,"s":[{"i":[[-15.301,0],[0,0],[0,17.262],[0,0],[15.301,0],[0,0],[0,-17.262],[0,0]],"o":[[0,0],[15.301,0],[0,0],[0,-17.262],[0,0],[-15.301,0],[0,0],[0,17.262]],"v":[[-24.286,61.26],[28.902,61.26],[56.607,30.004],[56.607,-30.004],[28.902,-61.26],[-24.286,-61.26],[-51.99,-30.004],[-51.99,30.004]],"c":true}]},{"i":{"x":0.667,"y":1},"o":{"x":0.333,"y":0},"t":20,"s":[{"i":[[-15.301,0],[0,0],[0,17.262],[0,0],[15.301,0],[0,0],[0,-17.262],[0,0]],"o":[[0,0],[15.301,0],[0,0],[0,-17.262],[0,0],[-15.301,0],[0,0],[0,17.262]],"v":[[-24.286,61.26],[28.902,61.26],[56.607,30.004],[56.607,-30.004],[28.902,-61.26],[-24.286,-61.26],[-51.99,-30.004],[-51.99,30.004]],"c":true}]},{"i":{"x":0.667,"y":1},"o":{"x":0.333,"y":0},"t":30,"s":[{"i":[[19.812,0],[0,0],[0,17.262],[0,0],[-19.812,0],[0,0],[0,-17.262],[0,0]],"o":[[0,0],[-19.812,0],[0,0],[0,-17.262],[0,0],[19.812,0],[0,0],[0,17.262]],"v":[[34.254,61.26],[-34.615,61.26],[-70.487,30.004],[-70.487,-30.004],[-34.615,-61.26],[34.254,-61.26],[70.126,-30.004],[70.126,30.004]],"c":true}]},{"i":{"x":0.667,"y":1},"o":{"x":0.333,"y":0},"t":40,"s":[{"i":[[15.666,0],[0,0],[0,17.262],[0,0],[-15.666,0],[0,0],[0,-17.262],[0,0]],"o":[[0,0],[-15.666,0],[0,0],[0,-17.262],[0,0],[15.666,0],[0,0],[0,17.262]],"v":[[27.343,61.26],[-27.117,61.26],[-55.483,30.004],[-55.483,-30.004],[-27.117,-61.26],[27.343,-61.26],[55.71,-30.004],[55.71,30.004]],"c":true}]},{"t":50,"s":[{"i":[[17.262,0],[0,0],[0,17.262],[0,0],[-17.262,0],[0,0],[0,-17.262],[0,0]],"o":[[0,0],[-17.262,0],[0,0],[0,-17.262],[0,0],[17.262,0],[0,0],[0,17.262]],"v":[[30.004,61.26],[-30.004,61.26],[-61.26,30.004],[-61.26,-30.004],[-30.004,-61.26],[30.004,-61.26],[61.26,-30.004],[61.26,30.004]],"c":true}]}],"ix":2},"nm":"Path 1","mn":"ADBE Vector Shape - Group","hd":false},{"ty":"st","c":{"a":0,"k":[0,0,0,1],"ix":3},"o":{"a":0,"k":100,"ix":4},"w":{"a":0,"k":35,"ix":5},"lc":1,"lj":1,"ml":10,"bm":0,"nm":"Stroke 1","mn":"ADBE Vector Graphic - Stroke","hd":false},{"ty":"tr","p":{"a":0,"k":[373.776,228.26],"ix":2},"a":{"a":0,"k":[0,0],"ix":1},"s":{"a":0,"k":[100,100],"ix":3},"r":{"a":0,"k":0,"ix":6},"o":{"a":0,"k":100,"ix":7},"sk":{"a":0,"k":0,"ix":4},"sa":{"a":0,"k":0,"ix":5},"nm":"Transform"}],"nm":"Group 1","np":2,"cix":2,"bm":0,"ix":1,"mn":"ADBE Vector Group","hd":false},{"ty":"gr","it":[{"ind":0,"ty":"sh","ix":1,"ks":{"a":1,"k":[{"i":{"x":0.667,"y":1},"o":{"x":0.333,"y":0},"t":0,"s":[{"i":[[-20.681,0],[0,-20.681],[20.681,0],[0,20.681]],"o":[[20.681,0],[0,20.681],[-20.681,0],[0,-20.681]],"v":[[0,-37.446],[37.446,0],[0,37.446],[-37.446,0]],"c":true}]},{"i":{"x":0.667,"y":1},"o":{"x":0.333,"y":0},"t":10,"s":[{"i":[[18.331,0],[0,-20.681],[-18.331,0],[0,20.681]],"o":[[-18.331,0],[0,20.681],[18.331,0],[0,-20.681]],"v":[[-384.011,-37.446],[-417.201,0],[-384.011,37.446],[-350.82,0]],"c":true}]},{"i":{"x":0.667,"y":1},"o":{"x":0.333,"y":0},"t":20,"s":[{"i":[[18.331,0],[0,-20.681],[-18.331,0],[0,20.681]],"o":[[-18.331,0],[0,20.681],[18.331,0],[0,-20.681]],"v":[[-384.011,-37.446],[-417.201,0],[-384.011,37.446],[-350.82,0]],"c":true}]},{"i":{"x":0.667,"y":1},"o":{"x":0.333,"y":0},"t":30,"s":[{"i":[[-23.735,0],[0,-20.681],[23.735,0],[0,20.681]],"o":[[23.735,0],[0,20.681],[-23.735,0],[0,-20.681]],"v":[[75.751,-37.446],[118.726,0],[75.751,37.446],[32.775,0]],"c":true}]},{"i":{"x":0.667,"y":1},"o":{"x":0.333,"y":0},"t":40,"s":[{"i":[[-18.769,0],[0,-20.681],[18.769,0],[0,20.681]],"o":[[18.769,0],[0,20.681],[-18.769,0],[0,-20.681]],"v":[[-18.82,-37.446],[15.164,0],[-18.82,37.446],[-52.804,0]],"c":true}]},{"t":50,"s":[{"i":[[-20.681,0],[0,-20.681],[20.681,0],[0,20.681]],"o":[[20.681,0],[0,20.681],[-20.681,0],[0,-20.681]],"v":[[0,-37.446],[37.446,0],[0,37.446],[-37.446,0]],"c":true}]}],"ix":2},"nm":"Path 1","mn":"ADBE Vector Shape - Group","hd":false},{"ty":"st","c":{"a":0,"k":[0,0,0,1],"ix":3},"o":{"a":0,"k":100,"ix":4},"w":{"a":0,"k":35,"ix":5},"lc":1,"lj":1,"ml":10,"bm":0,"nm":"Stroke 1","mn":"ADBE Vector Graphic - Stroke","hd":false},{"ty":"tr","p":{"a":0,"k":[578.572,210.562],"ix":2},"a":{"a":0,"k":[0,0],"ix":1},"s":{"a":0,"k":[100,100],"ix":3},"r":{"a":0,"k":0,"ix":6},"o":{"a":0,"k":100,"ix":7},"sk":{"a":0,"k":0,"ix":4},"sa":{"a":0,"k":0,"ix":5},"nm":"Transform"}],"nm":"Group 2","np":2,"cix":2,"bm":0,"ix":2,"mn":"ADBE Vector Group","hd":false},{"ty":"gr","it":[{"ind":0,"ty":"sh","ix":1,"ks":{"a":1,"k":[{"i":{"x":0.667,"y":1},"o":{"x":0.333,"y":0},"t":0,"s":[{"i":[[-20.681,0],[0,-20.681],[20.681,0],[0,20.681]],"o":[[20.681,0],[0,20.681],[-20.681,0],[0,-20.681]],"v":[[0,-37.446],[37.446,0],[0,37.446],[-37.446,0]],"c":true}]},{"i":{"x":0.667,"y":1},"o":{"x":0.333,"y":0},"t":10,"s":[{"i":[[18.331,0],[0,-20.681],[-18.331,0],[0,20.681]],"o":[[-18.331,0],[0,20.681],[18.331,0],[0,-20.681]],"v":[[387.215,-37.446],[354.025,0],[387.215,37.446],[420.406,0]],"c":true}]},{"i":{"x":0.667,"y":1},"o":{"x":0.333,"y":0},"t":20,"s":[{"i":[[18.331,0],[0,-20.681],[-18.331,0],[0,20.681]],"o":[[-18.331,0],[0,20.681],[18.331,0],[0,-20.681]],"v":[[387.215,-37.446],[354.025,0],[387.215,37.446],[420.406,0]],"c":true}]},{"i":{"x":0.667,"y":1},"o":{"x":0.333,"y":0},"t":30,"s":[{"i":[[-23.735,0],[0,-20.681],[23.735,0],[0,20.681]],"o":[[23.735,0],[0,20.681],[-23.735,0],[0,-20.681]],"v":[[-59.388,-37.446],[-16.413,0],[-59.388,37.446],[-102.364,0]],"c":true}]},{"i":{"x":0.667,"y":1},"o":{"x":0.333,"y":0},"t":40,"s":[{"i":[[-18.769,0],[0,-20.681],[18.769,0],[0,20.681]],"o":[[18.769,0],[0,20.681],[-18.769,0],[0,-20.681]],"v":[[18.977,-37.446],[52.961,0],[18.977,37.446],[-15.007,0]],"c":true}]},{"t":50,"s":[{"i":[[-20.681,0],[0,-20.681],[20.681,0],[0,20.681]],"o":[[20.681,0],[0,20.681],[-20.681,0],[0,-20.681]],"v":[[0,-37.446],[37.446,0],[0,37.446],[-37.446,0]],"c":true}]}],"ix":2},"nm":"Path 1","mn":"ADBE Vector Shape - Group","hd":false},{"ty":"st","c":{"a":0,"k":[0,0,0,1],"ix":3},"o":{"a":0,"k":100,"ix":4},"w":{"a":0,"k":35,"ix":5},"lc":1,"lj":1,"ml":10,"bm":0,"nm":"Stroke 1","mn":"ADBE Vector Graphic - Stroke","hd":false},{"ty":"tr","p":{"a":0,"k":[169.729,210.562],"ix":2},"a":{"a":0,"k":[0,0],"ix":1},"s":{"a":0,"k":[100,100],"ix":3},"r":{"a":0,"k":0,"ix":6},"o":{"a":0,"k":100,"ix":7},"sk":{"a":0,"k":0,"ix":4},"sa":{"a":0,"k":0,"ix":5},"nm":"Transform"}],"nm":"Group 3","np":2,"cix":2,"bm":0,"ix":3,"mn":"ADBE Vector Group","hd":false},{"ty":"gr","it":[{"ind":0,"ty":"sh","ix":1,"ks":{"a":1,"k":[{"i":{"x":0.667,"y":1},"o":{"x":0.333,"y":0},"t":0,"s":[{"i":[[0,0],[0,0]],"o":[[0,0],[0,0]],"v":[[-48.072,0],[48.072,0]],"c":false}]},{"i":{"x":0.667,"y":1},"o":{"x":0.333,"y":0},"t":10,"s":[{"i":[[0,0],[0,0]],"o":[[0,0],[0,0]],"v":[[262.34,0],[177.121,0]],"c":false}]},{"i":{"x":0.667,"y":1},"o":{"x":0.333,"y":0},"t":20,"s":[{"i":[[0,0],[0,0]],"o":[[0,0],[0,0]],"v":[[262.34,0],[177.121,0]],"c":false}]},{"i":{"x":0.667,"y":1},"o":{"x":0.333,"y":0},"t":30,"s":[{"i":[[0,0],[0,0]],"o":[[0,0],[0,0]],"v":[[-101.447,0],[37.969,0]],"c":false}]},{"i":{"x":0.667,"y":1},"o":{"x":0.333,"y":0},"t":40,"s":[{"i":[[0,0],[0,0]],"o":[[0,0],[0,0]],"v":[[-32.859,0],[54.396,0]],"c":false}]},{"t":50,"s":[{"i":[[0,0],[0,0]],"o":[[0,0],[0,0]],"v":[[-48.072,0],[48.072,0]],"c":false}]}],"ix":2},"nm":"Path 1","mn":"ADBE Vector Shape - Group","hd":false},{"ty":"st","c":{"a":0,"k":[0,0,0,1],"ix":3},"o":{"a":0,"k":100,"ix":4},"w":{"a":0,"k":35,"ix":5},"lc":1,"lj":1,"ml":10,"bm":0,"nm":"Stroke 1","mn":"ADBE Vector Graphic - Stroke","hd":false},{"ty":"tr","p":{"a":0,"k":[258.516,212.678],"ix":2},"a":{"a":0,"k":[0,0],"ix":1},"s":{"a":0,"k":[100,100],"ix":3},"r":{"a":0,"k":0,"ix":6},"o":{"a":0,"k":100,"ix":7},"sk":{"a":0,"k":0,"ix":4},"sa":{"a":0,"k":0,"ix":5},"nm":"Transform"}],"nm":"Group 4","np":2,"cix":2,"bm":0,"ix":4,"mn":"ADBE Vector Group","hd":false},{"ty":"gr","it":[{"ind":0,"ty":"sh","ix":1,"ks":{"a":1,"k":[{"i":{"x":0.667,"y":1},"o":{"x":0.333,"y":0},"t":0,"s":[{"i":[[0,0],[0,0]],"o":[[0,0],[0,0]],"v":[[-56.572,0],[56.572,0]],"c":false}]},{"i":{"x":0.667,"y":1},"o":{"x":0.333,"y":0},"t":10,"s":[{"i":[[0,0],[0,0]],"o":[[0,0],[0,0]],"v":[[-169.822,0],[-270.109,0]],"c":false}]},{"i":{"x":0.667,"y":1},"o":{"x":0.333,"y":0},"t":20,"s":[{"i":[[0,0],[0,0]],"o":[[0,0],[0,0]],"v":[[-169.822,0],[-270.109,0]],"c":false}]},{"i":{"x":0.667,"y":1},"o":{"x":0.333,"y":0},"t":30,"s":[{"i":[[0,0],[0,0]],"o":[[0,0],[0,0]],"v":[[-47.706,0],[127.835,0]],"c":false}]},{"i":{"x":0.667,"y":1},"o":{"x":0.333,"y":0},"t":40,"s":[{"i":[[0,0],[0,0]],"o":[[0,0],[0,0]],"v":[[-62.123,0],[40.562,0]],"c":false}]},{"t":50,"s":[{"i":[[0,0],[0,0]],"o":[[0,0],[0,0]],"v":[[-56.572,0],[56.572,0]],"c":false}]}],"ix":2},"nm":"Path 1","mn":"ADBE Vector Shape - Group","hd":false},{"ty":"st","c":{"a":0,"k":[0,0,0,1],"ix":3},"o":{"a":0,"k":100,"ix":4},"w":{"a":0,"k":35,"ix":5},"lc":1,"lj":1,"ml":10,"bm":0,"nm":"Stroke 1","mn":"ADBE Vector Graphic - Stroke","hd":false},{"ty":"tr","p":{"a":0,"k":[491.608,212.678],"ix":2},"a":{"a":0,"k":[0,0],"ix":1},"s":{"a":0,"k":[100,100],"ix":3},"r":{"a":0,"k":0,"ix":6},"o":{"a":0,"k":100,"ix":7},"sk":{"a":0,"k":0,"ix":4},"sa":{"a":0,"k":0,"ix":5},"nm":"Transform"}],"nm":"Group 5","np":2,"cix":2,"bm":0,"ix":5,"mn":"ADBE Vector Group","hd":false},{"ty":"tr","p":{"a":0,"k":[374.151,228.26],"ix":2},"a":{"a":0,"k":[374.151,228.26],"ix":1},"s":{"a":0,"k":[100,100],"ix":3},"r":{"a":0,"k":0,"ix":6},"o":{"a":0,"k":40,"ix":7},"sk":{"a":0,"k":0,"ix":4},"sa":{"a":0,"k":0,"ix":5},"nm":"Transform"}],"nm":"Group 10","np":5,"cix":2,"bm":0,"ix":1,"mn":"ADBE Vector Group","hd":false},{"ty":"gr","it":[{"ind":0,"ty":"sh","ix":1,"ks":{"a":1,"k":[{"i":{"x":0.667,"y":1},"o":{"x":0.333,"y":0},"t":0,"s":[{"i":[[13.604,0],[0,0],[0,13.604],[0,0],[-13.604,0],[0,0],[0,-13.604],[0,0]],"o":[[0,0],[-13.604,0],[0,0],[0,-13.604],[0,0],[13.604,0],[0,0],[0,13.604]],"v":[[16.067,40.699],[-16.067,40.699],[-40.699,16.067],[-40.699,-16.067],[-16.067,-40.699],[16.067,-40.699],[40.699,-16.067],[40.699,16.067]],"c":true}]},{"i":{"x":0.667,"y":1},"o":{"x":0.333,"y":0},"t":10,"s":[{"i":[[-12.058,0],[0,0],[0,13.604],[0,0],[12.058,0],[0,0],[0,-13.604],[0,0]],"o":[[0,0],[12.058,0],[0,0],[0,-13.604],[0,0],[-12.058,0],[0,0],[0,13.604]],"v":[[-471.648,40.699],[-443.165,40.699],[-421.332,16.067],[-421.332,-16.067],[-443.165,-40.699],[-471.648,-40.699],[-493.481,-16.067],[-493.481,16.067]],"c":true}]},{"i":{"x":0.667,"y":1},"o":{"x":0.333,"y":0},"t":20,"s":[{"i":[[-12.058,0],[0,0],[0,13.604],[0,0],[12.058,0],[0,0],[0,-13.604],[0,0]],"o":[[0,0],[12.058,0],[0,0],[0,-13.604],[0,0],[-12.058,0],[0,0],[0,13.604]],"v":[[-471.648,40.699],[-443.165,40.699],[-421.332,16.067],[-421.332,-16.067],[-443.165,-40.699],[-471.648,-40.699],[-493.481,-16.067],[-493.481,16.067]],"c":true}]},{"i":{"x":0.667,"y":1},"o":{"x":0.333,"y":0},"t":30,"s":[{"i":[[15.613,0],[0,0],[0,13.604],[0,0],[-15.613,0],[0,0],[0,-13.604],[0,0]],"o":[[0,0],[-15.613,0],[0,0],[0,-13.604],[0,0],[15.613,0],[0,0],[0,13.604]],"v":[[54.25,40.699],[17.37,40.699],[-10.899,16.067],[-10.899,-16.067],[17.37,-40.699],[54.25,-40.699],[82.519,-16.067],[82.519,16.067]],"c":true}]},{"i":{"x":0.667,"y":1},"o":{"x":0.333,"y":0},"t":40,"s":[{"i":[[12.346,0],[0,0],[0,13.604],[0,0],[-12.346,0],[0,0],[0,-13.604],[0,0]],"o":[[0,0],[-12.346,0],[0,0],[0,-13.604],[0,0],[12.346,0],[0,0],[0,13.604]],"v":[[-7.835,40.699],[-36.999,40.699],[-59.353,16.067],[-59.353,-16.067],[-36.999,-40.699],[-7.835,-40.699],[14.519,-16.067],[14.519,16.067]],"c":true}]},{"t":50,"s":[{"i":[[13.604,0],[0,0],[0,13.604],[0,0],[-13.604,0],[0,0],[0,-13.604],[0,0]],"o":[[0,0],[-13.604,0],[0,0],[0,-13.604],[0,0],[13.604,0],[0,0],[0,13.604]],"v":[[16.067,40.699],[-16.067,40.699],[-40.699,16.067],[-40.699,-16.067],[-16.067,-40.699],[16.067,-40.699],[40.699,-16.067],[40.699,16.067]],"c":true}]}],"ix":2},"nm":"Path 1","mn":"ADBE Vector Shape - Group","hd":false},{"ty":"st","c":{"a":0,"k":[0,0,0,1],"ix":3},"o":{"a":0,"k":100,"ix":4},"w":{"a":0,"k":35,"ix":5},"lc":1,"lj":1,"ml":10,"bm":0,"nm":"Stroke 1","mn":"ADBE Vector Graphic - Stroke","hd":false},{"ty":"tr","p":{"a":0,"k":[617.481,542.301],"ix":2},"a":{"a":0,"k":[0,0],"ix":1},"s":{"a":0,"k":[100,100],"ix":3},"r":{"a":0,"k":0,"ix":6},"o":{"a":0,"k":100,"ix":7},"sk":{"a":0,"k":0,"ix":4},"sa":{"a":0,"k":0,"ix":5},"nm":"Transform"}],"nm":"Group 6","np":2,"cix":2,"bm":0,"ix":2,"mn":"ADBE Vector Group","hd":false},{"ty":"gr","it":[{"ind":0,"ty":"sh","ix":1,"ks":{"a":1,"k":[{"i":{"x":0.667,"y":1},"o":{"x":0.333,"y":0},"t":0,"s":[{"i":[[13.604,0],[0,0],[0,13.604],[0,0],[-13.604,0],[0,0],[0,-13.604],[0,0]],"o":[[0,0],[-13.604,0],[0,0],[0,-13.604],[0,0],[13.604,0],[0,0],[0,13.604]],"v":[[16.067,40.699],[-16.067,40.699],[-40.699,16.067],[-40.699,-16.067],[-16.067,-40.699],[16.067,-40.699],[40.699,-16.067],[40.699,16.067]],"c":true}]},{"i":{"x":0.667,"y":1},"o":{"x":0.333,"y":0},"t":10,"s":[{"i":[[-12.058,0],[0,0],[0,13.604],[0,0],[12.058,0],[0,0],[0,-13.604],[0,0]],"o":[[0,0],[12.058,0],[0,0],[0,-13.604],[0,0],[-12.058,0],[0,0],[0,13.604]],"v":[[443.165,40.699],[471.648,40.699],[493.481,16.067],[493.481,-16.067],[471.648,-40.699],[443.165,-40.699],[421.333,-16.067],[421.333,16.067]],"c":true}]},{"i":{"x":0.667,"y":1},"o":{"x":0.333,"y":0},"t":20,"s":[{"i":[[-12.058,0],[0,0],[0,13.604],[0,0],[12.058,0],[0,0],[0,-13.604],[0,0]],"o":[[0,0],[12.058,0],[0,0],[0,-13.604],[0,0],[-12.058,0],[0,0],[0,13.604]],"v":[[443.165,40.699],[471.648,40.699],[493.481,16.067],[493.481,-16.067],[471.648,-40.699],[443.165,-40.699],[421.333,-16.067],[421.333,16.067]],"c":true}]},{"i":{"x":0.667,"y":1},"o":{"x":0.333,"y":0},"t":30,"s":[{"i":[[15.613,0],[0,0],[0,13.604],[0,0],[-15.613,0],[0,0],[0,-13.604],[0,0]],"o":[[0,0],[-15.613,0],[0,0],[0,-13.604],[0,0],[15.613,0],[0,0],[0,13.604]],"v":[[-17.37,40.699],[-54.25,40.699],[-82.519,16.067],[-82.519,-16.067],[-54.25,-40.699],[-17.37,-40.699],[10.899,-16.067],[10.899,16.067]],"c":true}]},{"i":{"x":0.667,"y":1},"o":{"x":0.333,"y":0},"t":40,"s":[{"i":[[12.346,0],[0,0],[0,13.604],[0,0],[-12.346,0],[0,0],[0,-13.604],[0,0]],"o":[[0,0],[-12.346,0],[0,0],[0,-13.604],[0,0],[12.346,0],[0,0],[0,13.604]],"v":[[36.999,40.699],[7.835,40.699],[-14.519,16.067],[-14.519,-16.067],[7.835,-40.699],[36.999,-40.699],[59.353,-16.067],[59.353,16.067]],"c":true}]},{"t":50,"s":[{"i":[[13.604,0],[0,0],[0,13.604],[0,0],[-13.604,0],[0,0],[0,-13.604],[0,0]],"o":[[0,0],[-13.604,0],[0,0],[0,-13.604],[0,0],[13.604,0],[0,0],[0,13.604]],"v":[[16.067,40.699],[-16.067,40.699],[-40.699,16.067],[-40.699,-16.067],[-16.067,-40.699],[16.067,-40.699],[40.699,-16.067],[40.699,16.067]],"c":true}]}],"ix":2},"nm":"Path 1","mn":"ADBE Vector Shape - Group","hd":false},{"ty":"st","c":{"a":0,"k":[0,0,0,1],"ix":3},"o":{"a":0,"k":100,"ix":4},"w":{"a":0,"k":35,"ix":5},"lc":1,"lj":1,"ml":10,"bm":0,"nm":"Stroke 1","mn":"ADBE Vector Graphic - Stroke","hd":false},{"ty":"tr","p":{"a":0,"k":[132.519,542.301],"ix":2},"a":{"a":0,"k":[0,0],"ix":1},"s":{"a":0,"k":[100,100],"ix":3},"r":{"a":0,"k":0,"ix":6},"o":{"a":0,"k":100,"ix":7},"sk":{"a":0,"k":0,"ix":4},"sa":{"a":0,"k":0,"ix":5},"nm":"Transform"}],"nm":"Group 7","np":2,"cix":2,"bm":0,"ix":3,"mn":"ADBE Vector Group","hd":false},{"ty":"gr","it":[{"ind":0,"ty":"sh","ix":1,"ks":{"a":1,"k":[{"i":{"x":0.667,"y":1},"o":{"x":0.333,"y":0},"t":0,"s":[{"i":[[0,0],[-103.596,31.734]],"o":[[0,-127.136],[0,0]],"v":[[-89.899,132.945],[89.899,-132.945]],"c":false}]},{"i":{"x":0.667,"y":1},"o":{"x":0.333,"y":0},"t":10,"s":[{"i":[[0,0],[91.824,31.734]],"o":[[0,-127.136],[0,0]],"v":[[372.124,132.945],[212.757,-132.945]],"c":false}]},{"i":{"x":0.667,"y":1},"o":{"x":0.333,"y":0},"t":20,"s":[{"i":[[0,0],[91.824,31.734]],"o":[[0,-127.136],[0,0]],"v":[[372.124,132.945],[212.757,-132.945]],"c":false}]},{"i":{"x":0.667,"y":1},"o":{"x":0.333,"y":0},"t":30,"s":[{"i":[[0,0],[-118.895,31.734]],"o":[[0,-127.136],[0,0]],"v":[[-126.071,132.945],[80.281,-132.945]],"c":false}]},{"i":{"x":0.667,"y":1},"o":{"x":0.333,"y":0},"t":40,"s":[{"i":[[0,0],[-94.019,31.734]],"o":[[0,-127.136],[0,0]],"v":[[-67.256,132.945],[95.92,-132.945]],"c":false}]},{"t":50,"s":[{"i":[[0,0],[-103.596,31.734]],"o":[[0,-127.136],[0,0]],"v":[[-89.899,132.945],[89.899,-132.945]],"c":false}]}],"ix":2},"nm":"Path 1","mn":"ADBE Vector Shape - Group","hd":false},{"ty":"st","c":{"a":0,"k":[0,0,0,1],"ix":3},"o":{"a":0,"k":100,"ix":4},"w":{"a":0,"k":35,"ix":5},"lc":1,"lj":1,"ml":10,"bm":0,"nm":"Stroke 1","mn":"ADBE Vector Graphic - Stroke","hd":false},{"ty":"tr","p":{"a":0,"k":[219.971,370.772],"ix":2},"a":{"a":0,"k":[0,0],"ix":1},"s":{"a":0,"k":[100,100],"ix":3},"r":{"a":0,"k":0,"ix":6},"o":{"a":0,"k":100,"ix":7},"sk":{"a":0,"k":0,"ix":4},"sa":{"a":0,"k":0,"ix":5},"nm":"Transform"}],"nm":"Group 8","np":2,"cix":2,"bm":0,"ix":4,"mn":"ADBE Vector Group","hd":false},{"ty":"gr","it":[{"ind":0,"ty":"sh","ix":1,"ks":{"a":1,"k":[{"i":{"x":0.667,"y":1},"o":{"x":0.333,"y":0},"t":0,"s":[{"i":[[0,0],[0,-125.829]],"o":[[101.969,32.934],[0,0]],"v":[[-88.306,-132.443],[88.306,132.443]],"c":false}]},{"i":{"x":0.667,"y":1},"o":{"x":0.333,"y":0},"t":10,"s":[{"i":[[0,0],[0,-125.829]],"o":[[-90.381,32.934],[0,0]],"v":[[-212.557,-132.443],[-369.1,132.443]],"c":false}]},{"i":{"x":0.667,"y":1},"o":{"x":0.333,"y":0},"t":20,"s":[{"i":[[0,0],[0,-125.829]],"o":[[-90.381,32.934],[0,0]],"v":[[-212.557,-132.443],[-369.1,132.443]],"c":false}]},{"i":{"x":0.667,"y":1},"o":{"x":0.333,"y":0},"t":30,"s":[{"i":[[0,0],[0,-125.829]],"o":[[117.028,32.934],[0,0]],"v":[[-78.579,-132.443],[124.116,132.443]],"c":false}]},{"i":{"x":0.667,"y":1},"o":{"x":0.333,"y":0},"t":40,"s":[{"i":[[0,0],[0,-125.829]],"o":[[92.542,32.934],[0,0]],"v":[[-94.396,-132.443],[65.889,132.443]],"c":false}]},{"t":50,"s":[{"i":[[0,0],[0,-125.829]],"o":[[101.969,32.934],[0,0]],"v":[[-88.306,-132.443],[88.306,132.443]],"c":false}]}],"ix":2},"nm":"Path 1","mn":"ADBE Vector Shape - Group","hd":false},{"ty":"st","c":{"a":0,"k":[0,0,0,1],"ix":3},"o":{"a":0,"k":100,"ix":4},"w":{"a":0,"k":35,"ix":5},"lc":1,"lj":1,"ml":10,"bm":0,"nm":"Stroke 1","mn":"ADBE Vector Graphic - Stroke","hd":false},{"ty":"tr","p":{"a":0,"k":[529.174,371.273],"ix":2},"a":{"a":0,"k":[0,0],"ix":1},"s":{"a":0,"k":[100,100],"ix":3},"r":{"a":0,"k":0,"ix":6},"o":{"a":0,"k":100,"ix":7},"sk":{"a":0,"k":0,"ix":4},"sa":{"a":0,"k":0,"ix":5},"nm":"Transform"}],"nm":"Group 9","np":2,"cix":2,"bm":0,"ix":5,"mn":"ADBE Vector Group","hd":false}],"ip":0,"op":180,"st":0,"ct":1,"bm":0}],"markers":[]}