{"v":"5.9.6","fr":60,"ip":0,"op":120,"w":750,"h":750,"nm":"Main render","ddd":0,"assets":[],"layers":[{"ddd":0,"ind":1,"ty":4,"nm":"Layer 1","sr":1,"ks":{"o":{"a":0,"k":100,"ix":11},"r":{"a":1,"k":[{"i":{"x":[0.667],"y":[1]},"o":{"x":[0.333],"y":[0]},"t":0,"s":[0]},{"i":{"x":[0.667],"y":[1]},"o":{"x":[0.333],"y":[0]},"t":13.334,"s":[20]},{"i":{"x":[0.667],"y":[1]},"o":{"x":[0.333],"y":[0]},"t":26.666,"s":[-20]},{"i":{"x":[0.667],"y":[1]},"o":{"x":[0.333],"y":[0]},"t":40,"s":[10]},{"t":53.333984375,"s":[0]}],"ix":10},"p":{"a":1,"k":[{"i":{"x":0.667,"y":1},"o":{"x":0.333,"y":0},"t":6.666,"s":[137.178,612.822,0],"to":[0,-10,0],"ti":[0,-10,0]},{"i":{"x":0.667,"y":1},"o":{"x":0.333,"y":0},"t":20,"s":[137.178,552.822,0],"to":[0,10,0],"ti":[0,-3.333,0]},{"i":{"x":0.667,"y":1},"o":{"x":0.333,"y":0},"t":33.334,"s":[137.178,672.822,0],"to":[0,3.333,0],"ti":[0,10,0]},{"i":{"x":0.667,"y":1},"o":{"x":0.333,"y":0},"t":46.666,"s":[137.178,572.822,0],"to":[0,-10,0],"ti":[0,-6.667,0]},{"t":60,"s":[137.178,612.822,0]}],"ix":2,"l":2},"a":{"a":0,"k":[-237.822,237.822,0],"ix":1,"l":2},"s":{"a":0,"k":[100,100,100],"ix":6,"l":2}},"ao":0,"shapes":[{"ty":"gr","it":[{"ind":0,"ty":"sh","ix":1,"ks":{"a":0,"k":{"i":[[0,0],[57.726,33.587],[-17.678,30.384],[0,0],[0,0],[0,0],[-9.144,-5.32],[0,0],[-4.627,7.953],[0,0],[0,0]],"o":[[-17.678,30.384],[-57.726,-33.587],[0,0],[0,0],[0,0],[-4.627,7.953],[0,0],[9.144,5.32],[0,0],[0,0],[0,0]],"v":[[95.959,66.723],[-40.573,60.923],[-113.087,-54.906],[-93.882,-87.915],[-28.701,-49.991],[-39.986,-30.596],[-31.808,-6.564],[17.389,22.061],[42.323,17.294],[56.351,-6.817],[117.908,28.998]],"c":true},"ix":2},"nm":"Path 1","mn":"ADBE Vector Shape - Group","hd":false},{"ty":"st","c":{"a":0,"k":[0,0,0,1],"ix":3},"o":{"a":0,"k":100,"ix":4},"w":{"a":0,"k":35,"ix":5},"lc":2,"lj":2,"bm":0,"nm":"Stroke 1","mn":"ADBE Vector Graphic - Stroke","hd":false},{"ty":"tr","p":{"a":0,"k":[0,0],"ix":2},"a":{"a":0,"k":[0,0],"ix":1},"s":{"a":0,"k":[100,100],"ix":3},"r":{"a":0,"k":0,"ix":6},"o":{"a":0,"k":40,"ix":7},"sk":{"a":0,"k":0,"ix":4},"sa":{"a":0,"k":0,"ix":5},"nm":"Transform"}],"nm":"Group 1","np":2,"cix":2,"bm":0,"ix":1,"mn":"ADBE Vector Group","hd":false},{"ty":"gr","it":[{"ind":0,"ty":"sh","ix":1,"ks":{"a":0,"k":{"i":[[131.346,0],[0,-131.346],[-40.296,-42.608],[0,0],[0,0],[-45.225,0],[0,131.345]],"o":[[-131.346,0],[0,63.274],[0,0],[0,0],[35.997,21.916],[131.346,0],[0,-131.346]],"v":[[0,-237.822],[-237.822,0],[-172.809,163.378],[-227.029,237.822],[-123.496,203.281],[0,237.822],[237.822,0]],"c":true},"ix":2},"nm":"Path 1","mn":"ADBE Vector Shape - Group","hd":false},{"ty":"st","c":{"a":0,"k":[0,0,0,1],"ix":3},"o":{"a":0,"k":100,"ix":4},"w":{"a":0,"k":35,"ix":5},"lc":2,"lj":2,"bm":0,"nm":"Stroke 1","mn":"ADBE Vector Graphic - Stroke","hd":false},{"ty":"tr","p":{"a":0,"k":[0,0],"ix":2},"a":{"a":0,"k":[0,0],"ix":1},"s":{"a":0,"k":[100,100],"ix":3},"r":{"a":0,"k":0,"ix":6},"o":{"a":0,"k":100,"ix":7},"sk":{"a":0,"k":0,"ix":4},"sa":{"a":0,"k":0,"ix":5},"nm":"Transform"}],"nm":"Group 2","np":2,"cix":2,"bm":0,"ix":2,"mn":"ADBE Vector Group","hd":false}],"ip":0,"op":180,"st":0,"ct":1,"bm":0}],"markers":[]}